{
  "schema_version": "1.1",
  "generated_at": "2026-04-16T16:00:00+08:00",
  "themes": [
    {
      "id": "storage_dram",
      "name": "存储芯片",
      "us_etfs": [
        "DRAM",
        "SOXX",
        "SMH"
      ],
      "primary_us": "DRAM",
      "primary_cn": "512480",
      "tags": [
        "DRAM",
        "NAND",
        "半导体"
      ],
      "note": "A股无纯存储基金, 用半导体宽主题替代",
      "returns": {
        "r_1d": 0.016400876253986722,
        "r_5d": 0.07894931095988335,
        "r_20d": null,
        "r_60d": null,
        "r_120d": null,
        "r_ytd": 0.23289414831262717
      },
      "strength": {
        "short": 92,
        "mid": 0,
        "long": 78,
        "composite": 50
      },
      "us_strength": {
        "short": 92,
        "mid": 0,
        "long": 78,
        "composite": 50
      },
      "cn_strength": {
        "short": 89,
        "mid": 70,
        "long": 69,
        "composite": 73
      },
      "rank": {
        "short": 16,
        "mid": 16,
        "long": 16,
        "composite": 16
      }
    },
    {
      "id": "semiconductor",
      "name": "半导体",
      "us_etfs": [
        "SOXX",
        "SMH",
        "XSD"
      ],
      "primary_us": "SOXX",
      "primary_cn": "512480",
      "tags": [
        "半导体",
        "芯片",
        "半导体设备"
      ],
      "note": "",
      "returns": {
        "r_1d": 0.010126267307765504,
        "r_5d": 0.06967053553938443,
        "r_20d": 0.18232643050482433,
        "r_60d": 0.18572494171776682,
        "r_120d": 0.35887818391154946,
        "r_ytd": 0.2584406942110939
      },
      "strength": {
        "short": 86,
        "mid": 99,
        "long": 92,
        "composite": 94
      },
      "us_strength": {
        "short": 86,
        "mid": 99,
        "long": 92,
        "composite": 94
      },
      "cn_strength": {
        "short": 89,
        "mid": 70,
        "long": 69,
        "composite": 73
      },
      "rank": {
        "short": 2,
        "mid": 2,
        "long": 2,
        "composite": 2
      }
    },
    {
      "id": "cybersecurity",
      "name": "网络安全",
      "us_etfs": [
        "CIBR",
        "BUG"
      ],
      "primary_us": "CIBR",
      "primary_cn": "512720",
      "tags": [
        "网络安全",
        "计算机"
      ],
      "note": "A股无纯网络安全 ETF, 映射纯度低",
      "returns": {
        "r_1d": 0.02146661755043141,
        "r_5d": 0.04403804784892466,
        "r_20d": 0.016407537955825717,
        "r_60d": -0.05803037408033342,
        "r_120d": -0.14383930021514504,
        "r_ytd": -0.0679833780564563
      },
      "strength": {
        "short": 83,
        "mid": 26,
        "long": 22,
        "composite": 36
      },
      "us_strength": {
        "short": 83,
        "mid": 26,
        "long": 22,
        "composite": 36
      },
      "cn_strength": {
        "short": 93,
        "mid": 39,
        "long": 53,
        "composite": 55
      },
      "rank": {
        "short": 21,
        "mid": 21,
        "long": 21,
        "composite": 21
      }
    },
    {
      "id": "ai_compute",
      "name": "AI算力",
      "us_etfs": [
        "THNQ",
        "AIQ",
        "QQQ"
      ],
      "primary_us": "THNQ",
      "primary_cn": "515980",
      "tags": [
        "AI",
        "人工智能",
        "算力"
      ],
      "note": "",
      "returns": {
        "r_1d": 0.01516628886667047,
        "r_5d": 0.10866213294358568,
        "r_20d": 0.10038806869367455,
        "r_60d": 0.06443130878806258,
        "r_120d": 0.0577651337688358,
        "r_ytd": 0.06085299735297308
      },
      "strength": {
        "short": 97,
        "mid": 79,
        "long": 50,
        "composite": 71
      },
      "us_strength": {
        "short": 97,
        "mid": 79,
        "long": 50,
        "composite": 71
      },
      "cn_strength": {
        "short": 97,
        "mid": 83,
        "long": 77,
        "composite": 83
      },
      "rank": {
        "short": 9,
        "mid": 9,
        "long": 9,
        "composite": 9
      }
    },
    {
      "id": "energy_oil",
      "name": "原油/油气",
      "us_etfs": [
        "XLE",
        "USO"
      ],
      "primary_us": "XLE",
      "primary_cn": "162411",
      "tags": [
        "原油",
        "油气",
        "能源"
      ],
      "note": "",
      "returns": {
        "r_1d": 0.01459887132324301,
        "r_5d": -0.013168463279332816,
        "r_20d": -0.02566141875304618,
        "r_60d": 0.1793352911343047,
        "r_120d": 0.2687418981385196,
        "r_ytd": 0.2211644278000649
      },
      "strength": {
        "short": 43,
        "mid": 75,
        "long": 81,
        "composite": 71
      },
      "us_strength": {
        "short": 43,
        "mid": 75,
        "long": 81,
        "composite": 71
      },
      "cn_strength": {
        "short": 2,
        "mid": 95,
        "long": 89,
        "composite": 74
      },
      "rank": {
        "short": 10,
        "mid": 10,
        "long": 10,
        "composite": 10
      }
    },
    {
      "id": "cn_coal",
      "name": "煤炭",
      "us_etfs": [],
      "primary_us": null,
      "primary_cn": "515220",
      "tags": [
        "煤炭",
        "能源",
        "红利"
      ],
      "note": "",
      "returns": {
        "r_1d": 0.0025073143097835457,
        "r_5d": 0.004182356577478352,
        "r_20d": -0.043289731791516475,
        "r_60d": 0.10276696103618646,
        "r_120d": 0.02450481720332608,
        "r_ytd": 0.1472187236070202
      },
      "strength": {
        "short": 43,
        "mid": 76,
        "long": 66,
        "composite": 65
      },
      "us_strength": null,
      "cn_strength": {
        "short": 43,
        "mid": 76,
        "long": 66,
        "composite": 65
      },
      "rank": {
        "short": 11,
        "mid": 11,
        "long": 11,
        "composite": 11
      }
    },
    {
      "id": "new_energy_vehicle",
      "name": "新能源车",
      "us_etfs": [
        "DRIV",
        "HAIL"
      ],
      "primary_us": "DRIV",
      "primary_cn": "515030",
      "tags": [
        "新能源车",
        "智能出行"
      ],
      "note": "",
      "returns": {
        "r_1d": 0.023135769888081303,
        "r_5d": 0.06954431316463956,
        "r_20d": 0.14518109481648125,
        "r_60d": 0.0887281549579469,
        "r_120d": 0.20366237020108557,
        "r_ytd": 0.1383621390937092
      },
      "strength": {
        "short": 89,
        "mid": 87,
        "long": 69,
        "composite": 80
      },
      "us_strength": {
        "short": 89,
        "mid": 87,
        "long": 69,
        "composite": 80
      },
      "cn_strength": {
        "short": 98,
        "mid": 90,
        "long": 72,
        "composite": 84
      },
      "rank": {
        "short": 6,
        "mid": 6,
        "long": 6,
        "composite": 6
      }
    },
    {
      "id": "cn_battery",
      "name": "锂电池",
      "us_etfs": [
        "LIT"
      ],
      "primary_us": "LIT",
      "primary_cn": "159755",
      "tags": [
        "锂电池",
        "储能"
      ],
      "note": "",
      "returns": {
        "r_1d": 0.03297610579132512,
        "r_5d": 0.07006952034188142,
        "r_20d": 0.16988555206488404,
        "r_60d": 0.16199733527407972,
        "r_120d": 0.38091252748481286,
        "r_ytd": 0.2167553218787081
      },
      "strength": {
        "short": 94,
        "mid": 97,
        "long": 89,
        "composite": 93
      },
      "us_strength": {
        "short": 94,
        "mid": 97,
        "long": 89,
        "composite": 93
      },
      "cn_strength": {
        "short": 99,
        "mid": 97,
        "long": 79,
        "composite": 90
      },
      "rank": {
        "short": 3,
        "mid": 3,
        "long": 3,
        "composite": 3
      }
    },
    {
      "id": "cn_chemicals",
      "name": "化工",
      "us_etfs": [],
      "primary_us": null,
      "primary_cn": "159870",
      "tags": [
        "化工",
        "新材料",
        "周期"
      ],
      "note": "国内化工细分（无窄口径美股锚点，cn_only）",
      "returns": {
        "r_1d": 0.014404681202548394,
        "r_5d": 0.009950330853168092,
        "r_20d": 0.012175025875279235,
        "r_60d": 0.0659329656041047,
        "r_120d": 0.2843871765549284,
        "r_ytd": 0.08731145201063623
      },
      "strength": {
        "short": 68,
        "mid": 80,
        "long": 86,
        "composite": 80
      },
      "us_strength": null,
      "cn_strength": {
        "short": 68,
        "mid": 80,
        "long": 86,
        "composite": 80
      },
      "rank": {
        "short": 7,
        "mid": 7,
        "long": 7,
        "composite": 7
      }
    },
    {
      "id": "robotics",
      "name": "机器人",
      "us_etfs": [
        "BOTZ",
        "ROBO",
        "ARKQ"
      ],
      "primary_us": "BOTZ",
      "primary_cn": "562500",
      "tags": [
        "机器人",
        "智能制造"
      ],
      "note": "",
      "returns": {
        "r_1d": -0.000544674799350061,
        "r_5d": 0.04998949403359016,
        "r_20d": 0.05199607914694372,
        "r_60d": -0.012452762478243291,
        "r_120d": 0.0010449893735833265,
        "r_ytd": 0.0
      },
      "strength": {
        "short": 78,
        "mid": 53,
        "long": 36,
        "composite": 51
      },
      "us_strength": {
        "short": 78,
        "mid": 53,
        "long": 36,
        "composite": 51
      },
      "cn_strength": {
        "short": 87,
        "mid": 35,
        "long": 46,
        "composite": 50
      },
      "rank": {
        "short": 14,
        "mid": 14,
        "long": 14,
        "composite": 14
      }
    },
    {
      "id": "gold",
      "name": "黄金",
      "us_etfs": [
        "GLD",
        "SLV"
      ],
      "primary_us": "GLD",
      "primary_cn": "518880",
      "tags": [
        "黄金",
        "贵金属",
        "避险"
      ],
      "note": "",
      "returns": {
        "r_1d": -0.0008631178955779131,
        "r_5d": 0.004943079881876749,
        "r_20d": -0.010533321738059846,
        "r_60d": 0.006497100498570448,
        "r_120d": 0.15396888394170186,
        "r_ytd": 0.09980122560022524
      },
      "strength": {
        "short": 52,
        "mid": 39,
        "long": 63,
        "composite": 51
      },
      "us_strength": {
        "short": 52,
        "mid": 39,
        "long": 63,
        "composite": 51
      },
      "cn_strength": {
        "short": 65,
        "mid": 50,
        "long": 57,
        "composite": 56
      },
      "rank": {
        "short": 15,
        "mid": 15,
        "long": 15,
        "composite": 15
      }
    },
    {
      "id": "cn_base_metals",
      "name": "有色金属",
      "us_etfs": [
        "PICK"
      ],
      "primary_us": "PICK",
      "primary_cn": "512400",
      "tags": [
        "有色",
        "工业金属"
      ],
      "note": "A股有色对应美股金属矿业",
      "returns": {
        "r_1d": 0.0023928492670616864,
        "r_5d": 0.03041313155409422,
        "r_20d": 0.13544524183396597,
        "r_60d": 0.10330890549018985,
        "r_120d": 0.34593479287960255,
        "r_ytd": 0.18117496097622332
      },
      "strength": {
        "short": 75,
        "mid": 90,
        "long": 85,
        "composite": 85
      },
      "us_strength": {
        "short": 75,
        "mid": 90,
        "long": 85,
        "composite": 85
      },
      "cn_strength": {
        "short": 85,
        "mid": 74,
        "long": 84,
        "composite": 80
      },
      "rank": {
        "short": 5,
        "mid": 5,
        "long": 5,
        "composite": 5
      }
    },
    {
      "id": "china_internet",
      "name": "中概互联网/港股",
      "us_etfs": [
        "KWEB",
        "CQQQ"
      ],
      "primary_us": "KWEB",
      "primary_cn": "513050",
      "tags": [
        "中概",
        "港股",
        "互联网"
      ],
      "note": "",
      "returns": {
        "r_1d": 0.01540040459251491,
        "r_5d": 0.044497048003973125,
        "r_20d": 0.021831248424384123,
        "r_60d": -0.14996540155419355,
        "r_120d": -0.21162289545638605,
        "r_ytd": -0.168662825167476
      },
      "strength": {
        "short": 81,
        "mid": 9,
        "long": 13,
        "composite": 25
      },
      "us_strength": {
        "short": 81,
        "mid": 9,
        "long": 13,
        "composite": 25
      },
      "cn_strength": {
        "short": 92,
        "mid": 4,
        "long": 11,
        "composite": 24
      },
      "rank": {
        "short": 29,
        "mid": 29,
        "long": 29,
        "composite": 29
      }
    },
    {
      "id": "cn_brokerage",
      "name": "券商",
      "us_etfs": [],
      "primary_us": null,
      "primary_cn": "512000",
      "tags": [
        "券商",
        "金融",
        "高 beta"
      ],
      "note": "",
      "returns": {
        "r_1d": 0.003883500026397612,
        "r_5d": 0.04559759143887267,
        "r_20d": -0.03241465868428182,
        "r_60d": -0.142454640064067,
        "r_120d": -0.1340157714182023,
        "r_ytd": -0.1340157714182023
      },
      "strength": {
        "short": 80,
        "mid": 11,
        "long": 21,
        "composite": 29
      },
      "us_strength": null,
      "cn_strength": {
        "short": 80,
        "mid": 11,
        "long": 21,
        "composite": 29
      },
      "rank": {
        "short": 25,
        "mid": 25,
        "long": 25,
        "composite": 25
      }
    },
    {
      "id": "cn_banking",
      "name": "银行",
      "us_etfs": [
        "KBE",
        "KRE"
      ],
      "primary_us": "KBE",
      "primary_cn": "512800",
      "tags": [
        "银行",
        "金融",
        "高股息"
      ],
      "note": "A股银行对应美股商业+区域银行",
      "returns": {
        "r_1d": -0.0037956413760400244,
        "r_5d": -0.007734209333618639,
        "r_20d": 0.09805011556331976,
        "r_60d": 0.018261402147301875,
        "r_120d": 0.11350435955461878,
        "r_ytd": 0.03704744384947062
      },
      "strength": {
        "short": 15,
        "mid": 70,
        "long": 54,
        "composite": 53
      },
      "us_strength": {
        "short": 15,
        "mid": 70,
        "long": 54,
        "composite": 53
      },
      "cn_strength": {
        "short": 60,
        "mid": 51,
        "long": 43,
        "composite": 50
      },
      "rank": {
        "short": 13,
        "mid": 13,
        "long": 13,
        "composite": 13
      }
    },
    {
      "id": "cn_insurance",
      "name": "保险",
      "us_etfs": [
        "KIE",
        "IAK"
      ],
      "primary_us": "KIE",
      "primary_cn": "159851",
      "tags": [
        "保险",
        "金融",
        "大金融"
      ],
      "note": "A股保险对应美股保险（KIE 与 KBE 同 SPDR 系列）",
      "returns": {
        "r_1d": 0.004867863997221529,
        "r_5d": 0.013444148592980798,
        "r_20d": 0.05070609127363888,
        "r_60d": -0.0033516146130633077,
        "r_120d": 0.017620156701784573,
        "r_ytd": -0.026302035352977073
      },
      "strength": {
        "short": 68,
        "mid": 57,
        "long": 33,
        "composite": 50
      },
      "us_strength": {
        "short": 68,
        "mid": 57,
        "long": 33,
        "composite": 50
      },
      "cn_strength": {
        "short": 82,
        "mid": 2,
        "long": 19,
        "composite": 25
      },
      "rank": {
        "short": 17,
        "mid": 17,
        "long": 17,
        "composite": 17
      }
    },
    {
      "id": "solar_clean_energy",
      "name": "光伏/清洁能源",
      "us_etfs": [
        "TAN",
        "ICLN"
      ],
      "primary_us": "TAN",
      "primary_cn": "515790",
      "tags": [
        "光伏",
        "清洁能源"
      ],
      "note": "",
      "returns": {
        "r_1d": -0.01511727188178878,
        "r_5d": -0.0042120662242515995,
        "r_20d": -0.03763836883743122,
        "r_60d": 0.05662958274224684,
        "r_120d": 0.1704633639928307,
        "r_ytd": 0.05449558648199444
      },
      "strength": {
        "short": 9,
        "mid": 46,
        "long": 59,
        "composite": 44
      },
      "us_strength": {
        "short": 9,
        "mid": 46,
        "long": 59,
        "composite": 44
      },
      "cn_strength": {
        "short": 83,
        "mid": 55,
        "long": 75,
        "composite": 69
      },
      "rank": {
        "short": 18,
        "mid": 18,
        "long": 18,
        "composite": 18
      }
    },
    {
      "id": "biotech",
      "name": "生物科技/创新药",
      "us_etfs": [
        "IBB",
        "XBI"
      ],
      "primary_us": "XBI",
      "primary_cn": "512290",
      "tags": [
        "生物科技",
        "创新药",
        "医药"
      ],
      "note": "",
      "returns": {
        "r_1d": -0.007281739637682847,
        "r_5d": 0.027239025485607124,
        "r_20d": 0.11197718619271685,
        "r_60d": 0.0780454010451421,
        "r_120d": 0.23616428588045665,
        "r_ytd": 0.10859760300181531
      },
      "strength": {
        "short": 71,
        "mid": 83,
        "long": 72,
        "composite": 76
      },
      "us_strength": {
        "short": 71,
        "mid": 83,
        "long": 72,
        "composite": 76
      },
      "cn_strength": {
        "short": 66,
        "mid": 37,
        "long": 36,
        "composite": 42
      },
      "rank": {
        "short": 8,
        "mid": 8,
        "long": 8,
        "composite": 8
      }
    },
    {
      "id": "aerospace_defense",
      "name": "航天军工",
      "us_etfs": [
        "ITA",
        "UFO",
        "ARKX"
      ],
      "primary_us": "ITA",
      "primary_cn": "512660",
      "tags": [
        "航天",
        "军工",
        "国防"
      ],
      "note": "",
      "returns": {
        "r_1d": -0.02146808751968943,
        "r_5d": -0.011849303053256828,
        "r_20d": -0.010424448295075007,
        "r_60d": -0.03734852367639876,
        "r_120d": 0.08482617411567309,
        "r_ytd": 0.0317794337983753
      },
      "strength": {
        "short": 3,
        "mid": 22,
        "long": 47,
        "composite": 28
      },
      "us_strength": {
        "short": 3,
        "mid": 22,
        "long": 47,
        "composite": 28
      },
      "cn_strength": {
        "short": 75,
        "mid": 20,
        "long": 59,
        "composite": 47
      },
      "rank": {
        "short": 28,
        "mid": 28,
        "long": 28,
        "composite": 28
      }
    },
    {
      "id": "rare_earth",
      "name": "稀土/新材料",
      "us_etfs": [
        "REMX",
        "PICK"
      ],
      "primary_us": "REMX",
      "primary_cn": "516780",
      "tags": [
        "稀土",
        "新材料"
      ],
      "note": "",
      "returns": {
        "r_1d": 0.05597750793373896,
        "r_5d": 0.10046664800344592,
        "r_20d": 0.17310655493129648,
        "r_60d": 0.14086396220213074,
        "r_120d": 0.42326160878099006,
        "r_ytd": 0.294270163276869
      },
      "strength": {
        "short": 99,
        "mid": 94,
        "long": 96,
        "composite": 96
      },
      "us_strength": {
        "short": 99,
        "mid": 94,
        "long": 96,
        "composite": 96
      },
      "cn_strength": {
        "short": 78,
        "mid": 45,
        "long": 64,
        "composite": 59
      },
      "rank": {
        "short": 1,
        "mid": 1,
        "long": 1,
        "composite": 1
      }
    },
    {
      "id": "cn_rare_metals",
      "name": "稀有金属",
      "us_etfs": [],
      "primary_us": null,
      "primary_cn": "159608",
      "tags": [
        "稀有金属",
        "锂",
        "钴",
        "钨钼",
        "锡",
        "小金属"
      ],
      "note": "跟踪中证稀有金属主题指数(930632)，权重含锂(>13%)、钴、稀土(>15%)、钨、锡等；与 rare_earth(纯稀土产业链)和 cn_base_metals(铜铝铅锌)成份差异显著；cn_only",
      "returns": {
        "r_1d": 0.03925213548513499,
        "r_5d": 0.06155789299943316,
        "r_20d": 0.08951397026602328,
        "r_60d": 0.05988844352989219,
        "r_120d": 0.3160998657712059,
        "r_ytd": 0.14879713828217614
      },
      "strength": {
        "short": 95,
        "mid": 92,
        "long": 92,
        "composite": 93
      },
      "us_strength": null,
      "cn_strength": {
        "short": 95,
        "mid": 92,
        "long": 92,
        "composite": 93
      },
      "rank": {
        "short": 4,
        "mid": 4,
        "long": 4,
        "composite": 4
      }
    },
    {
      "id": "cn_liquor",
      "name": "白酒",
      "us_etfs": [],
      "primary_us": null,
      "primary_cn": "512690",
      "tags": [
        "白酒",
        "主要消费"
      ],
      "note": "",
      "returns": {
        "r_1d": 0.0020304575503819213,
        "r_5d": 0.006103782938017886,
        "r_20d": -0.039766671128079426,
        "r_60d": -0.10576611290532557,
        "r_120d": -0.1880522315029396,
        "r_ytd": -0.10210980170221505
      },
      "strength": {
        "short": 47,
        "mid": 18,
        "long": 17,
        "composite": 23
      },
      "us_strength": null,
      "cn_strength": {
        "short": 47,
        "mid": 18,
        "long": 17,
        "composite": 23
      },
      "rank": {
        "short": 30,
        "mid": 30,
        "long": 30,
        "composite": 30
      }
    },
    {
      "id": "cn_consumer",
      "name": "大消费",
      "us_etfs": [
        "XLP",
        "XLY",
        "VDC"
      ],
      "primary_us": "XLP",
      "primary_cn": "159928",
      "tags": [
        "消费",
        "大消费",
        "宽口径"
      ],
      "note": "大消费宽口径板块：跨必选(主要消费)+可选；A股侧 159928/510150/159936 多锚点；美股侧 XLP(必选,与159928口径最近)+XLY(可选)+VDC(必选替代)，primary_us=XLP 对称 primary_cn=159928",
      "returns": {
        "r_1d": 0.004554090796938964,
        "r_5d": -0.02450389543148085,
        "r_20d": -0.009137114925056835,
        "r_60d": -0.005743196881662361,
        "r_120d": 0.03457611526074626,
        "r_ytd": 0.052630150768112165
      },
      "strength": {
        "short": 6,
        "mid": 34,
        "long": 43,
        "composite": 32
      },
      "us_strength": {
        "short": 6,
        "mid": 34,
        "long": 43,
        "composite": 32
      },
      "cn_strength": {
        "short": 51,
        "mid": 28,
        "long": 28,
        "composite": 33
      },
      "rank": {
        "short": 23,
        "mid": 23,
        "long": 23,
        "composite": 23
      }
    },
    {
      "id": "cn_consumer_staples",
      "name": "主要消费",
      "us_etfs": [],
      "primary_us": null,
      "primary_cn": "159928",
      "tags": [
        "消费",
        "食品饮料"
      ],
      "note": "",
      "returns": {
        "r_1d": 0.0013289038500537342,
        "r_5d": 0.00800004266707637,
        "r_20d": -0.03778951274541753,
        "r_60d": -0.05804336964991527,
        "r_120d": -0.11290173020196187,
        "r_ytd": -0.06304338006662094
      },
      "strength": {
        "short": 51,
        "mid": 28,
        "long": 28,
        "composite": 33
      },
      "us_strength": null,
      "cn_strength": {
        "short": 51,
        "mid": 28,
        "long": 28,
        "composite": 33
      },
      "rank": {
        "short": 22,
        "mid": 22,
        "long": 22,
        "composite": 22
      }
    },
    {
      "id": "cn_medical_devices",
      "name": "医疗器械",
      "us_etfs": [],
      "primary_us": null,
      "primary_cn": "159883",
      "tags": [
        "医疗器械",
        "医药"
      ],
      "note": "",
      "returns": {
        "r_1d": 0.006230549750636163,
        "r_5d": 0.004149383546811618,
        "r_20d": -0.03858346603915659,
        "r_60d": -0.1262586332954429,
        "r_120d": -0.09286035289359493,
        "r_ytd": -0.06995858860691047
      },
      "strength": {
        "short": 55,
        "mid": 15,
        "long": 31,
        "composite": 29
      },
      "us_strength": null,
      "cn_strength": {
        "short": 55,
        "mid": 15,
        "long": 31,
        "composite": 29
      },
      "rank": {
        "short": 26,
        "mid": 26,
        "long": 26,
        "composite": 26
      }
    },
    {
      "id": "cn_home_appliances",
      "name": "家电",
      "us_etfs": [],
      "primary_us": null,
      "primary_cn": "159996",
      "tags": [
        "家电",
        "可选消费"
      ],
      "note": "",
      "returns": {
        "r_1d": 0.00685873744984131,
        "r_5d": 0.02211562146367342,
        "r_20d": -0.03029514754777697,
        "r_60d": -0.08888931181382992,
        "r_120d": 0.0006837607104006278,
        "r_ytd": -0.07566910038569521
      },
      "strength": {
        "short": 70,
        "mid": 23,
        "long": 40,
        "composite": 39
      },
      "us_strength": null,
      "cn_strength": {
        "short": 70,
        "mid": 23,
        "long": 40,
        "composite": 39
      },
      "rank": {
        "short": 19,
        "mid": 19,
        "long": 19,
        "composite": 19
      }
    },
    {
      "id": "cn_real_estate",
      "name": "房地产",
      "us_etfs": [],
      "primary_us": null,
      "primary_cn": "512200",
      "tags": [
        "地产"
      ],
      "note": "",
      "returns": {
        "r_1d": 0.0029006546806373116,
        "r_5d": 0.034625926933723045,
        "r_20d": -0.05972972903730469,
        "r_60d": -0.10767499665629715,
        "r_120d": -0.14469262460046198,
        "r_ytd": -0.09194728058810199
      },
      "strength": {
        "short": 72,
        "mid": 13,
        "long": 24,
        "composite": 29
      },
      "us_strength": null,
      "cn_strength": {
        "short": 72,
        "mid": 13,
        "long": 24,
        "composite": 29
      },
      "rank": {
        "short": 27,
        "mid": 27,
        "long": 27,
        "composite": 27
      }
    },
    {
      "id": "cn_media",
      "name": "传媒",
      "us_etfs": [],
      "primary_us": null,
      "primary_cn": "159805",
      "tags": [
        "传媒",
        "广告",
        "TMT"
      ],
      "note": "传媒宽口径（含出版/广电/广告）；游戏专项见 cn_gaming",
      "returns": {
        "r_1d": 0.02392795369523556,
        "r_5d": 0.01753815559646441,
        "r_20d": -0.01723586273913242,
        "r_60d": -0.22063693532414083,
        "r_120d": 0.08259580178403848,
        "r_ytd": -0.020647670893468917
      },
      "strength": {
        "short": 73,
        "mid": 8,
        "long": 51,
        "composite": 38
      },
      "us_strength": null,
      "cn_strength": {
        "short": 73,
        "mid": 8,
        "long": 51,
        "composite": 38
      },
      "rank": {
        "short": 20,
        "mid": 20,
        "long": 20,
        "composite": 20
      }
    },
    {
      "id": "cn_gaming",
      "name": "游戏动漫",
      "us_etfs": [],
      "primary_us": null,
      "primary_cn": "159869",
      "tags": [
        "游戏",
        "动漫",
        "TMT"
      ],
      "note": "国内手游为主，中美游戏成份股差异大，cn_only",
      "returns": {
        "r_1d": 0.025507759547212665,
        "r_5d": 0.022472855852058576,
        "r_20d": -0.024873264745139574,
        "r_60d": -0.22225426712932553,
        "r_120d": -0.036367644170874715,
        "r_ytd": -0.10802363307730999
      },
      "strength": {
        "short": 77,
        "mid": 6,
        "long": 34,
        "composite": 31
      },
      "us_strength": null,
      "cn_strength": {
        "short": 77,
        "mid": 6,
        "long": 34,
        "composite": 31
      },
      "rank": {
        "short": 24,
        "mid": 24,
        "long": 24,
        "composite": 24
      }
    },
    {
      "id": "cn_power",
      "name": "电力",
      "us_etfs": [],
      "primary_us": null,
      "primary_cn": "561560",
      "tags": [
        "电力",
        "公用事业",
        "红利"
      ],
      "note": "",
      "returns": {
        "r_1d": 0.003009784062904197,
        "r_5d": 0.0189615085587353,
        "r_20d": -0.03904731778250323,
        "r_60d": 0.0595920972022456,
        "r_120d": 0.057202609804864316,
        "r_ytd": 0.0854416786635711
      },
      "strength": {
        "short": 63,
        "mid": 62,
        "long": 61,
        "composite": 62
      },
      "us_strength": null,
      "cn_strength": {
        "short": 63,
        "mid": 62,
        "long": 61,
        "composite": 62
      },
      "rank": {
        "short": 12,
        "mid": 12,
        "long": 12,
        "composite": 12
      }
    }
  ]
}